[
    {
        "Name": "FnatInflation",
        "Winrate": 44.0,
        "Gold": 9051.44,
        "Tier": "P",
        "Division": 2,
        "Damage": 33964.8
    },
    {
        "Name": "Sidestep Joe",
        "Winrate": 44.0,
        "Gold": 7388.28,
        "Tier": "M",
        "Division": 0,
        "Damage": 20645.3
    },
    {
        "Name": "avusaenanos",
        "Winrate": 56.00000000000001,
        "Gold": 8817.66,
        "Tier": "D",
        "Division": 1,
        "Damage": 21755.18
    },
    {
        "Name": "Lyesoo",
        "Winrate": 54.0,
        "Gold": 7735.98,
        "Tier": "M",
        "Division": 0,
        "Damage": 16841.56
    },
    {
        "Name": "Krydd Hasse",
        "Winrate": 54.0,
        "Gold": 8438.72,
        "Tier": "D",
        "Division": 2,
        "Damage": 19591.4
    },
    {
        "Name": "HS tchokez",
        "Winrate": 52.0,
        "Gold": 7459.98,
        "Tier": "M",
        "Division": 0,
        "Damage": 24653.1
    },
    {
        "Name": "0741",
        "Winrate": 46.0,
        "Gold": 7816.08,
        "Tier": "D",
        "Division": 2,
        "Damage": 24134.72
    },
    {
        "Name": "Alllu",
        "Winrate": 56.00000000000001,
        "Gold": 7939.06,
        "Tier": "M",
        "Division": 0,
        "Damage": 28600.26
    },
    {
        "Name": "Hyakki v1",
        "Winrate": 57.99999999999999,
        "Gold": 8775.72,
        "Tier": "D",
        "Division": 2,
        "Damage": 31825.2
    },
    {
        "Name": "Echios tiltproof",
        "Winrate": 60.0,
        "Gold": 7996.64,
        "Tier": "M",
        "Division": 0,
        "Damage": 22770.5
    },
    {
        "Name": "Zed Seto",
        "Winrate": 40.0,
        "Gold": 9919.52,
        "Tier": "P",
        "Division": 4,
        "Damage": 36327.84
    },
    {
        "Name": "Le Savage",
        "Winrate": 50.0,
        "Gold": 8422.54,
        "Tier": "S",
        "Division": 2,
        "Damage": 36522.72
    },
    {
        "Name": "ALENTERIX",
        "Winrate": 57.99999999999999,
        "Gold": 7932.84,
        "Tier": "S",
        "Division": 1,
        "Damage": 17875.52
    },
    {
        "Name": "Amn3ziA31",
        "Winrate": 38.0,
        "Gold": 8745.68,
        "Tier": "S",
        "Division": 4,
        "Damage": 44977.28
    },
    {
        "Name": "KDS Andy",
        "Winrate": 52.0,
        "Gold": 7943.18,
        "Tier": "G",
        "Division": 4,
        "Damage": 25900.12
    },
    {
        "Name": "\u00c5ku",
        "Winrate": 60.0,
        "Gold": 9850.5,
        "Tier": "G",
        "Division": 4,
        "Damage": 69030.26
    },
    {
        "Name": "cybersdorf",
        "Winrate": 54.0,
        "Gold": 8756.56,
        "Tier": "G",
        "Division": 3,
        "Damage": 43174.92
    },
    {
        "Name": "i dream lucid",
        "Winrate": 44.0,
        "Gold": 7585.52,
        "Tier": "C",
        "Division": 0,
        "Damage": 18697.72
    },
    {
        "Name": "Veignorem",
        "Winrate": 66.0,
        "Gold": 8124.58,
        "Tier": "C",
        "Division": 0,
        "Damage": 18672.22
    },
    {
        "Name": "death ends",
        "Winrate": 70.0,
        "Gold": 11509.12,
        "Tier": "C",
        "Division": 0,
        "Damage": 29609.54
    },
    {
        "Name": "fastFF",
        "Winrate": 56.00000000000001,
        "Gold": 7544.26,
        "Tier": "C",
        "Division": 0,
        "Damage": 14418.34
    },
    {
        "Name": "Scarlet Rose",
        "Winrate": 56.00000000000001,
        "Gold": 7001.1,
        "Tier": "C",
        "Division": 0,
        "Damage": 18541.06
    },
    {
        "Name": "Aladyah",
        "Winrate": 54.0,
        "Gold": 7803.3,
        "Tier": "P",
        "Division": 1,
        "Damage": 24485.5
    },
    {
        "Name": "IcedBelle",
        "Winrate": 54.0,
        "Gold": 8142.72,
        "Tier": "P",
        "Division": 4,
        "Damage": 23137.48
    },
    {
        "Name": "lysox98",
        "Winrate": 50.0,
        "Gold": 8065.66,
        "Tier": "P",
        "Division": 4,
        "Damage": 31099.5
    },
    {
        "Name": "paoloss",
        "Winrate": 30.0,
        "Gold": 8240.44,
        "Tier": "B",
        "Division": 4,
        "Damage": 21052.34
    },
    {
        "Name": "Shouhunter",
        "Winrate": 54.0,
        "Gold": 8280.16,
        "Tier": "B",
        "Division": 3,
        "Damage": 36014.52
    },
    {
        "Name": "Willa Woods",
        "Winrate": 54.0,
        "Gold": 9502.16,
        "Tier": "B",
        "Division": 2,
        "Damage": 50546.34
    },
    {
        "Name": "USE Dreamer Ace",
        "Winrate": 57.99999999999999,
        "Gold": 8314.36,
        "Tier": "GM",
        "Division": 0,
        "Damage": 23022.42
    },
    {
        "Name": "SaNTaS",
        "Winrate": 60.0,
        "Gold": 7819.78,
        "Tier": "GM",
        "Division": 0,
        "Damage": 25030.66
    },
    {
        "Name": "FtNx SanPan",
        "Winrate": 57.99999999999999,
        "Gold": 7822.06,
        "Tier": "GM",
        "Division": 0,
        "Damage": 23383.74
    },
    {
        "Name": "Helpful Slipper",
        "Winrate": 56.00000000000001,
        "Gold": 7349.98,
        "Tier": "GM",
        "Division": 0,
        "Damage": 23342.68
    },
    {
        "Name": "Rychly",
        "Winrate": 68.0,
        "Gold": 7860.34,
        "Tier": "GM",
        "Division": 0,
        "Damage": 22241.4
    },
    {
        "Name": "WinwinNcy",
        "Winrate": 50.0,
        "Gold": 7837.72,
        "Tier": "I",
        "Division": 1,
        "Damage": 25606.32
    },
    {
        "Name": "ActimelDraft",
        "Winrate": 40.0,
        "Gold": 6607.34,
        "Tier": "I",
        "Division": 4,
        "Damage": 16216.28
    },
    {
        "Name": "metalling",
        "Winrate": 38.0,
        "Gold": 8092.38,
        "Tier": "I",
        "Division": 4,
        "Damage": 37553.68
    },
    {
        "Name": "Tufooo",
        "Winrate": 50.0,
        "Gold": 8485.62,
        "Tier": "I",
        "Division": 4,
        "Damage": 54548.4
    },
    {
        "Name": "kattt",
        "Winrate": 48.0,
        "Gold": 9365.44,
        "Tier": "I",
        "Division": 2,
        "Damage": 50073.1
    }
]